[{"mSpeed":0,"mCalorie":0,"mDistance":0,"mWalkStepCount":0,"mNowHealthyStep":0,"mTotalActiveTime":0,"mTimeUnit":600000,"mStepCount":0,"mRunStepCount":0,"mStartTime":0},{"mSpeed":0,"mCalorie":0,"mDistance":0,"mWalkStepCount":0,"mNowHealthyStep":0,"mTotalActiveTime":0,"mTimeUnit":600000,"mStepCount":0,"mRunStepCount":0,"mStartTime":0},{"mSpeed":0,"mCalorie":0,"mDistance":0,"mWalkStepCount":0,"mNowHealthyStep":0,"mTotalActiveTime":0,"mTimeUnit":600000,"mStepCount":0,"mRunStepCount":0,"mStartTime":0},{"mSpeed":0,"mCalorie":0,"mDistance":0,"mWalkStepCount":0,"mNowHealthyStep":0,"mTotalActiveTime":0,"mTimeUnit":600000,"mStepCount":0,"mRunStepCount":0,"mStartTime":0},{"mSpeed":0,"mCalorie":0,"mDistance":0,"mWalkStepCount":0,"mNowHealthyStep":0,"mTotalActiveTime":0,"mTimeUnit":600000,"mStepCount":0,"mRunStepCount":0,"mStartTime":0},{"mSpeed":0,"mCalorie":0,"mDistance":0,"mWalkStepCount":0,"mNowHealthyStep":0,"mTotalActiveTime":0,"mTimeUnit":600000,"mStepCount":0,"mRunStepCount":0,"mStartTime":0},{"mSpeed":0,"mCalorie":0,"mDistance":0,"mWalkStepCount":0,"mNowHealthyStep":0,"mTotalActiveTime":0,"mTimeUnit":600000,"mStepCount":0,"mRunStepCount":0,"mStartTime":0},{"mSpeed":0,"mCalorie":0,"mDistance":0,"mWalkStepCount":0,"mNowHealthyStep":0,"mTotalActiveTime":0,"mTimeUnit":600000,"mStepCount":0,"mRunStepCount":0,"mStartTime":0},{"mSpeed":0,"mCalorie":0,"mDistance":0,"mWalkStepCount":0,"mNowHealthyStep":0,"mTotalActiveTime":0,"mTimeUnit":600000,"mStepCount":0,"mRunStepCount":0,"mStartTime":0},{"mSpeed":0,"mCalorie":0,"mDistance":0,"mWalkStepCount":0,"mNowHealthyStep":0,"mTotalActiveTime":0,"mTimeUnit":600000,"mStepCount":0,"mRunStepCount":0,"mStartTime":0},{"mSpeed":0,"mCalorie":0,"mDistance":0,"mWalkStepCount":0,"mNowHealthyStep":0,"mTotalActiveTime":0,"mTimeUnit":600000,"mStepCount":0,"mRunStepCount":0,"mStartTime":0},{"mSpeed":0,"mCalorie":0,"mDistance":0,"mWalkStepCount":0,"mNowHealthyStep":0,"mTotalActiveTime":0,"mTimeUnit":600000,"mStepCount":0,"mRunStepCount":0,"mStartTime":0},{"mSpeed":0,"mCalorie":0,"mDistance":0,"mWalkStepCount":0,"mNowHealthyStep":0,"mTotalActiveTime":0,"mTimeUnit":600000,"mStepCount":0,"mRunStepCount":0,"mStartTime":0},{"mSpeed":0,"mCalorie":0,"mDistance":0,"mWalkStepCount":0,"mNowHealthyStep":0,"mTotalActiveTime":0,"mTimeUnit":600000,"mStepCount":0,"mRunStepCount":0,"mStartTime":0},{"mSpeed":0,"mCalorie":0,"mDistance":0,"mWalkStepCount":0,"mNowHealthyStep":0,"mTotalActiveTime":0,"mTimeUnit":600000,"mStepCount":0,"mRunStepCount":0,"mStartTime":0},{"mSpeed":0,"mCalorie":0,"mDistance":0,"mWalkStepCount":0,"mNowHealthyStep":0,"mTotalActiveTime":0,"mTimeUnit":600000,"mStepCount":0,"mRunStepCount":0,"mStartTime":0},{"mSpeed":0,"mCalorie":0,"mDistance":0,"mWalkStepCount":0,"mNowHealthyStep":0,"mTotalActiveTime":0,"mTimeUnit":600000,"mStepCount":0,"mRunStepCount":0,"mStartTime":0},{"mSpeed":0,"mCalorie":0,"mDistance":0,"mWalkStepCount":0,"mNowHealthyStep":0,"mTotalActiveTime":0,"mTimeUnit":600000,"mStepCount":0,"mRunStepCount":0,"mStartTime":0},{"mSpeed":0,"mCalorie":0,"mDistance":0,"mWalkStepCount":0,"mNowHealthyStep":0,"mTotalActiveTime":0,"mTimeUnit":600000,"mStepCount":0,"mRunStepCount":0,"mStartTime":0},{"mSpeed":0,"mCalorie":0,"mDistance":0,"mWalkStepCount":0,"mNowHealthyStep":0,"mTotalActiveTime":0,"mTimeUnit":600000,"mStepCount":0,"mRunStepCount":0,"mStartTime":0},{"mSpeed":0,"mCalorie":0,"mDistance":0,"mWalkStepCount":0,"mNowHealthyStep":0,"mTotalActiveTime":0,"mTimeUnit":600000,"mStepCount":0,"mRunStepCount":0,"mStartTime":0},{"mSpeed":0,"mCalorie":0,"mDistance":0,"mWalkStepCount":0,"mNowHealthyStep":0,"mTotalActiveTime":0,"mTimeUnit":600000,"mStepCount":0,"mRunStepCount":0,"mStartTime":0},{"mSpeed":0,"mCalorie":0,"mDistance":0,"mWalkStepCount":0,"mNowHealthyStep":0,"mTotalActiveTime":0,"mTimeUnit":600000,"mStepCount":0,"mRunStepCount":0,"mStartTime":0},{"mSpeed":0,"mCalorie":0,"mDistance":0,"mWalkStepCount":0,"mNowHealthyStep":0,"mTotalActiveTime":0,"mTimeUnit":600000,"mStepCount":0,"mRunStepCount":0,"mStartTime":0},{"mSpeed":0,"mCalorie":0,"mDistance":0,"mWalkStepCount":0,"mNowHealthyStep":0,"mTotalActiveTime":0,"mTimeUnit":600000,"mStepCount":0,"mRunStepCount":0,"mStartTime":0},{"mSpeed":0,"mCalorie":0,"mDistance":0,"mWalkStepCount":0,"mNowHealthyStep":0,"mTotalActiveTime":0,"mTimeUnit":600000,"mStepCount":0,"mRunStepCount":0,"mStartTime":0},{"mSpeed":0,"mCalorie":0,"mDistance":0,"mWalkStepCount":0,"mNowHealthyStep":0,"mTotalActiveTime":0,"mTimeUnit":600000,"mStepCount":0,"mRunStepCount":0,"mStartTime":0},{"mSpeed":0,"mCalorie":0,"mDistance":0,"mWalkStepCount":0,"mNowHealthyStep":0,"mTotalActiveTime":0,"mTimeUnit":600000,"mStepCount":0,"mRunStepCount":0,"mStartTime":0},{"mSpeed":0,"mCalorie":0,"mDistance":0,"mWalkStepCount":0,"mNowHealthyStep":0,"mTotalActiveTime":0,"mTimeUnit":600000,"mStepCount":0,"mRunStepCount":0,"mStartTime":0},{"mSpeed":0,"mCalorie":0,"mDistance":0,"mWalkStepCount":0,"mNowHealthyStep":0,"mTotalActiveTime":0,"mTimeUnit":600000,"mStepCount":0,"mRunStepCount":0,"mStartTime":0},{"mSpeed":0,"mCalorie":0,"mDistance":0,"mWalkStepCount":0,"mNowHealthyStep":0,"mTotalActiveTime":0,"mTimeUnit":600000,"mStepCount":0,"mRunStepCount":0,"mStartTime":0},{"mSpeed":0,"mCalorie":0,"mDistance":0,"mWalkStepCount":0,"mNowHealthyStep":0,"mTotalActiveTime":0,"mTimeUnit":600000,"mStepCount":0,"mRunStepCount":0,"mStartTime":0},{"mSpeed":0,"mCalorie":0,"mDistance":0,"mWalkStepCount":0,"mNowHealthyStep":0,"mTotalActiveTime":0,"mTimeUnit":600000,"mStepCount":0,"mRunStepCount":0,"mStartTime":0},{"mSpeed":0,"mCalorie":0,"mDistance":0,"mWalkStepCount":0,"mNowHealthyStep":0,"mTotalActiveTime":0,"mTimeUnit":600000,"mStepCount":0,"mRunStepCount":0,"mStartTime":0},{"mSpeed":0,"mCalorie":0,"mDistance":0,"mWalkStepCount":0,"mNowHealthyStep":0,"mTotalActiveTime":0,"mTimeUnit":600000,"mStepCount":0,"mRunStepCount":0,"mStartTime":0},{"mSpeed":0,"mCalorie":0,"mDistance":0,"mWalkStepCount":0,"mNowHealthyStep":0,"mTotalActiveTime":0,"mTimeUnit":600000,"mStepCount":0,"mRunStepCount":0,"mStartTime":0},{"mSpeed":0,"mCalorie":0,"mDistance":0,"mWalkStepCount":0,"mNowHealthyStep":0,"mTotalActiveTime":0,"mTimeUnit":600000,"mStepCount":0,"mRunStepCount":0,"mStartTime":0},{"mSpeed":0,"mCalorie":0,"mDistance":0,"mWalkStepCount":0,"mNowHealthyStep":0,"mTotalActiveTime":0,"mTimeUnit":600000,"mStepCount":0,"mRunStepCount":0,"mStartTime":0},{"mSpeed":0,"mCalorie":0,"mDistance":0,"mWalkStepCount":0,"mNowHealthyStep":0,"mTotalActiveTime":0,"mTimeUnit":600000,"mStepCount":0,"mRunStepCount":0,"mStartTime":0},{"mSpeed":0,"mCalorie":0,"mDistance":0,"mWalkStepCount":0,"mNowHealthyStep":0,"mTotalActiveTime":0,"mTimeUnit":600000,"mStepCount":0,"mRunStepCount":0,"mStartTime":0},{"mSpeed":0,"mCalorie":0,"mDistance":0,"mWalkStepCount":0,"mNowHealthyStep":0,"mTotalActiveTime":0,"mTimeUnit":600000,"mStepCount":0,"mRunStepCount":0,"mStartTime":0},{"mSpeed":0,"mCalorie":0,"mDistance":0,"mWalkStepCount":0,"mNowHealthyStep":0,"mTotalActiveTime":0,"mTimeUnit":600000,"mStepCount":0,"mRunStepCount":0,"mStartTime":0},{"mSpeed":0,"mCalorie":0,"mDistance":0,"mWalkStepCount":0,"mNowHealthyStep":0,"mTotalActiveTime":0,"mTimeUnit":600000,"mStepCount":0,"mRunStepCount":0,"mStartTime":0},{"mSpeed":0,"mCalorie":0,"mDistance":0,"mWalkStepCount":0,"mNowHealthyStep":0,"mTotalActiveTime":0,"mTimeUnit":600000,"mStepCount":0,"mRunStepCount":0,"mStartTime":0},{"mSpeed":0,"mCalorie":0,"mDistance":0,"mWalkStepCount":0,"mNowHealthyStep":0,"mTotalActiveTime":0,"mTimeUnit":600000,"mStepCount":0,"mRunStepCount":0,"mStartTime":0},{"mSpeed":0,"mCalorie":0,"mDistance":0,"mWalkStepCount":0,"mNowHealthyStep":0,"mTotalActiveTime":0,"mTimeUnit":600000,"mStepCount":0,"mRunStepCount":0,"mStartTime":0},{"mSpeed":0,"mCalorie":0,"mDistance":0,"mWalkStepCount":0,"mNowHealthyStep":0,"mTotalActiveTime":0,"mTimeUnit":600000,"mStepCount":0,"mRunStepCount":0,"mStartTime":0},{"mSpeed":0,"mCalorie":0,"mDistance":0,"mWalkStepCount":0,"mNowHealthyStep":0,"mTotalActiveTime":0,"mTimeUnit":600000,"mStepCount":0,"mRunStepCount":0,"mStartTime":0},{"mSpeed":0,"mCalorie":0,"mDistance":0,"mWalkStepCount":0,"mNowHealthyStep":0,"mTotalActiveTime":0,"mTimeUnit":600000,"mStepCount":0,"mRunStepCount":0,"mStartTime":0},{"mSpeed":0,"mCalorie":0,"mDistance":0,"mWalkStepCount":0,"mNowHealthyStep":0,"mTotalActiveTime":0,"mTimeUnit":600000,"mStepCount":0,"mRunStepCount":0,"mStartTime":0},{"mSpeed":0,"mCalorie":0,"mDistance":0,"mWalkStepCount":0,"mNowHealthyStep":0,"mTotalActiveTime":0,"mTimeUnit":600000,"mStepCount":0,"mRunStepCount":0,"mStartTime":0},{"mSpeed":0,"mCalorie":0,"mDistance":0,"mWalkStepCount":0,"mNowHealthyStep":0,"mTotalActiveTime":0,"mTimeUnit":600000,"mStepCount":0,"mRunStepCount":0,"mStartTime":0},{"mSpeed":0,"mCalorie":0,"mDistance":0,"mWalkStepCount":0,"mNowHealthyStep":0,"mTotalActiveTime":0,"mTimeUnit":600000,"mStepCount":0,"mRunStepCount":0,"mStartTime":0},{"mSpeed":0,"mCalorie":0,"mDistance":0,"mWalkStepCount":0,"mNowHealthyStep":0,"mTotalActiveTime":0,"mTimeUnit":600000,"mStepCount":0,"mRunStepCount":0,"mStartTime":0},{"mSpeed":1.7167067527770996,"mCalorie":0.93032199999999998,"mDistance":13.300000000000001,"mWalkStepCount":16,"mNowHealthyStep":0,"mTotalActiveTime":27890.610858578497,"mTimeUnit":600000,"mStepCount":16,"mRunStepCount":0,"mStartTime":0},{"mSpeed":0,"mCalorie":0,"mDistance":0,"mWalkStepCount":0,"mNowHealthyStep":0,"mTotalActiveTime":0,"mTimeUnit":600000,"mStepCount":0,"mRunStepCount":0,"mStartTime":0},{"mSpeed":0,"mCalorie":0,"mDistance":0,"mWalkStepCount":0,"mNowHealthyStep":0,"mTotalActiveTime":0,"mTimeUnit":600000,"mStepCount":0,"mRunStepCount":0,"mStartTime":0},{"mSpeed":1.949799656867981,"mCalorie":0.43872800000000001,"mDistance":7.04,"mWalkStepCount":8,"mNowHealthyStep":0,"mTotalActiveTime":12998.258518883316,"mTimeUnit":600000,"mStepCount":8,"mRunStepCount":0,"mStartTime":0},{"mSpeed":0,"mCalorie":0,"mDistance":0,"mWalkStepCount":0,"mNowHealthyStep":0,"mTotalActiveTime":0,"mTimeUnit":600000,"mStepCount":0,"mRunStepCount":0,"mStartTime":0},{"mSpeed":4.3349113464355469,"mCalorie":1.4523239999999999,"mDistance":30.16,"mWalkStepCount":35,"mNowHealthyStep":0,"mTotalActiveTime":25046.879006944037,"mTimeUnit":600000,"mStepCount":35,"mRunStepCount":0,"mStartTime":0},{"mSpeed":0,"mCalorie":0,"mDistance":0,"mWalkStepCount":0,"mNowHealthyStep":0,"mTotalActiveTime":0,"mTimeUnit":600000,"mStepCount":0,"mRunStepCount":0,"mStartTime":0},{"mSpeed":0,"mCalorie":0,"mDistance":0,"mWalkStepCount":0,"mNowHealthyStep":0,"mTotalActiveTime":0,"mTimeUnit":600000,"mStepCount":0,"mRunStepCount":0,"mStartTime":0},{"mSpeed":0,"mCalorie":0,"mDistance":0,"mWalkStepCount":0,"mNowHealthyStep":0,"mTotalActiveTime":0,"mTimeUnit":600000,"mStepCount":0,"mRunStepCount":0,"mStartTime":0},{"mSpeed":0,"mCalorie":0,"mDistance":0,"mWalkStepCount":0,"mNowHealthyStep":0,"mTotalActiveTime":0,"mTimeUnit":600000,"mStepCount":0,"mRunStepCount":0,"mStartTime":0},{"mSpeed":0,"mCalorie":0,"mDistance":0,"mWalkStepCount":0,"mNowHealthyStep":0,"mTotalActiveTime":0,"mTimeUnit":600000,"mStepCount":0,"mRunStepCount":0,"mStartTime":0},{"mSpeed":0,"mCalorie":0,"mDistance":0,"mWalkStepCount":0,"mNowHealthyStep":0,"mTotalActiveTime":0,"mTimeUnit":600000,"mStepCount":0,"mRunStepCount":0,"mStartTime":0},{"mSpeed":0,"mCalorie":0,"mDistance":0,"mWalkStepCount":0,"mNowHealthyStep":0,"mTotalActiveTime":0,"mTimeUnit":600000,"mStepCount":0,"mRunStepCount":0,"mStartTime":0},{"mSpeed":0,"mCalorie":0,"mDistance":0,"mWalkStepCount":0,"mNowHealthyStep":0,"mTotalActiveTime":0,"mTimeUnit":600000,"mStepCount":0,"mRunStepCount":0,"mStartTime":0},{"mSpeed":0,"mCalorie":0,"mDistance":0,"mWalkStepCount":0,"mNowHealthyStep":0,"mTotalActiveTime":0,"mTimeUnit":600000,"mStepCount":0,"mRunStepCount":0,"mStartTime":0},{"mSpeed":2.0917439460754395,"mCalorie":1.0217369999999999,"mDistance":16.219854000000002,"mWalkStepCount":25,"mNowHealthyStep":0,"mTotalActiveTime":27915.211376399555,"mTimeUnit":600000,"mStepCount":25,"mRunStepCount":0,"mStartTime":0},{"mSpeed":6.0714287757873535,"mCalorie":17.573853999999997,"mDistance":405.30013600000001,"mWalkStepCount":459,"mNowHealthyStep":0,"mTotalActiveTime":240319.12208001936,"mTimeUnit":600000,"mStepCount":459,"mRunStepCount":0,"mStartTime":0},{"mSpeed":0,"mCalorie":0,"mDistance":0,"mWalkStepCount":0,"mNowHealthyStep":0,"mTotalActiveTime":0,"mTimeUnit":600000,"mStepCount":0,"mRunStepCount":0,"mStartTime":0},{"mSpeed":6.3974690437316895,"mCalorie":7.9057239999999993,"mDistance":185.95423599999998,"mWalkStepCount":191,"mNowHealthyStep":0,"mTotalActiveTime":104640.64015126304,"mTimeUnit":600000,"mStepCount":191,"mRunStepCount":0,"mStartTime":0},{"mSpeed":6.0071320533752441,"mCalorie":23.152580000000004,"mDistance":533.81091800000002,"mWalkStepCount":587,"mNowHealthyStep":0,"mTotalActiveTime":319906.27531619545,"mTimeUnit":600000,"mStepCount":587,"mRunStepCount":0,"mStartTime":0},{"mSpeed":0,"mCalorie":0,"mDistance":0,"mWalkStepCount":0,"mNowHealthyStep":0,"mTotalActiveTime":0,"mTimeUnit":600000,"mStepCount":0,"mRunStepCount":0,"mStartTime":0},{"mSpeed":0,"mCalorie":0,"mDistance":0,"mWalkStepCount":0,"mNowHealthyStep":0,"mTotalActiveTime":0,"mTimeUnit":600000,"mStepCount":0,"mRunStepCount":0,"mStartTime":0},{"mSpeed":0,"mCalorie":0,"mDistance":0,"mWalkStepCount":0,"mNowHealthyStep":0,"mTotalActiveTime":0,"mTimeUnit":600000,"mStepCount":0,"mRunStepCount":0,"mStartTime":0},{"mSpeed":0,"mCalorie":0,"mDistance":0,"mWalkStepCount":0,"mNowHealthyStep":0,"mTotalActiveTime":0,"mTimeUnit":600000,"mStepCount":0,"mRunStepCount":0,"mStartTime":0},{"mSpeed":0,"mCalorie":0,"mDistance":0,"mWalkStepCount":0,"mNowHealthyStep":0,"mTotalActiveTime":0,"mTimeUnit":600000,"mStepCount":0,"mRunStepCount":0,"mStartTime":0},{"mSpeed":0,"mCalorie":0,"mDistance":0,"mWalkStepCount":0,"mNowHealthyStep":0,"mTotalActiveTime":0,"mTimeUnit":600000,"mStepCount":0,"mRunStepCount":0,"mStartTime":0},{"mSpeed":0,"mCalorie":0,"mDistance":0,"mWalkStepCount":0,"mNowHealthyStep":0,"mTotalActiveTime":0,"mTimeUnit":600000,"mStepCount":0,"mRunStepCount":0,"mStartTime":0},{"mSpeed":0,"mCalorie":0,"mDistance":0,"mWalkStepCount":0,"mNowHealthyStep":0,"mTotalActiveTime":0,"mTimeUnit":600000,"mStepCount":0,"mRunStepCount":0,"mStartTime":0},{"mSpeed":0,"mCalorie":0,"mDistance":0,"mWalkStepCount":0,"mNowHealthyStep":0,"mTotalActiveTime":0,"mTimeUnit":600000,"mStepCount":0,"mRunStepCount":0,"mStartTime":0},{"mSpeed":2.2645297050476074,"mCalorie":1.142658,"mDistance":18.360001,"mWalkStepCount":28,"mNowHealthyStep":0,"mTotalActiveTime":29187.518915151722,"mTimeUnit":600000,"mStepCount":28,"mRunStepCount":0,"mStartTime":0},{"mSpeed":4.9804072380065918,"mCalorie":23.397822999999999,"mDistance":509.79999599999996,"mWalkStepCount":658,"mNowHealthyStep":0,"mTotalActiveTime":368499.98883024789,"mTimeUnit":600000,"mStepCount":658,"mRunStepCount":0,"mStartTime":0},{"mSpeed":0,"mCalorie":0,"mDistance":0,"mWalkStepCount":0,"mNowHealthyStep":0,"mTotalActiveTime":0,"mTimeUnit":600000,"mStepCount":0,"mRunStepCount":0,"mStartTime":0},{"mSpeed":5.6909146308898926,"mCalorie":2.8809690000000003,"mDistance":65.900001000000003,"mWalkStepCount":75,"mNowHealthyStep":0,"mTotalActiveTime":41687.501470674557,"mTimeUnit":600000,"mStepCount":75,"mRunStepCount":0,"mStartTime":0},{"mSpeed":2.9902303218841553,"mCalorie":2.0084109999999997,"mDistance":37.299999999999997,"mWalkStepCount":54,"mNowHealthyStep":0,"mTotalActiveTime":44906.241534952904,"mTimeUnit":600000,"mStepCount":54,"mRunStepCount":0,"mStartTime":0},{"mSpeed":3.1483223438262939,"mCalorie":0.33166499999999999,"mDistance":6.5999999999999996,"mWalkStepCount":10,"mNowHealthyStep":0,"mTotalActiveTime":7546.8765282539107,"mTimeUnit":600000,"mStepCount":10,"mRunStepCount":0,"mStartTime":0},{"mSpeed":0,"mCalorie":0,"mDistance":0,"mWalkStepCount":0,"mNowHealthyStep":0,"mTotalActiveTime":0,"mTimeUnit":600000,"mStepCount":0,"mRunStepCount":0,"mStartTime":0},{"mSpeed":5.3278417587280273,"mCalorie":0.93879699999999999,"mDistance":21.02,"mWalkStepCount":26,"mNowHealthyStep":0,"mTotalActiveTime":14203.124534626941,"mTimeUnit":600000,"mStepCount":26,"mRunStepCount":0,"mStartTime":0},{"mSpeed":0,"mCalorie":0,"mDistance":0,"mWalkStepCount":0,"mNowHealthyStep":0,"mTotalActiveTime":0,"mTimeUnit":600000,"mStepCount":0,"mRunStepCount":0,"mStartTime":0},{"mSpeed":0,"mCalorie":0,"mDistance":0,"mWalkStepCount":0,"mNowHealthyStep":0,"mTotalActiveTime":0,"mTimeUnit":600000,"mStepCount":0,"mRunStepCount":0,"mStartTime":0},{"mSpeed":0,"mCalorie":0,"mDistance":0,"mWalkStepCount":0,"mNowHealthyStep":0,"mTotalActiveTime":0,"mTimeUnit":600000,"mStepCount":0,"mRunStepCount":0,"mStartTime":0},{"mSpeed":0,"mCalorie":0,"mDistance":0,"mWalkStepCount":0,"mNowHealthyStep":0,"mTotalActiveTime":0,"mTimeUnit":600000,"mStepCount":0,"mRunStepCount":0,"mStartTime":0},{"mSpeed":0,"mCalorie":0,"mDistance":0,"mWalkStepCount":0,"mNowHealthyStep":0,"mTotalActiveTime":0,"mTimeUnit":600000,"mStepCount":0,"mRunStepCount":0,"mStartTime":0},{"mSpeed":0,"mCalorie":0,"mDistance":0,"mWalkStepCount":0,"mNowHealthyStep":0,"mTotalActiveTime":0,"mTimeUnit":600000,"mStepCount":0,"mRunStepCount":0,"mStartTime":0},{"mSpeed":0,"mCalorie":0,"mDistance":0,"mWalkStepCount":0,"mNowHealthyStep":0,"mTotalActiveTime":0,"mTimeUnit":600000,"mStepCount":0,"mRunStepCount":0,"mStartTime":0},{"mSpeed":0,"mCalorie":0,"mDistance":0,"mWalkStepCount":0,"mNowHealthyStep":0,"mTotalActiveTime":0,"mTimeUnit":600000,"mStepCount":0,"mRunStepCount":0,"mStartTime":0},{"mSpeed":0,"mCalorie":0,"mDistance":0,"mWalkStepCount":0,"mNowHealthyStep":0,"mTotalActiveTime":0,"mTimeUnit":600000,"mStepCount":0,"mRunStepCount":0,"mStartTime":0},{"mSpeed":0,"mCalorie":0,"mDistance":0,"mWalkStepCount":0,"mNowHealthyStep":0,"mTotalActiveTime":0,"mTimeUnit":600000,"mStepCount":0,"mRunStepCount":0,"mStartTime":0},{"mSpeed":0,"mCalorie":0,"mDistance":0,"mWalkStepCount":0,"mNowHealthyStep":0,"mTotalActiveTime":0,"mTimeUnit":600000,"mStepCount":0,"mRunStepCount":0,"mStartTime":0},{"mSpeed":1.8669202327728271,"mCalorie":0.752722,"mDistance":11.02,"mWalkStepCount":13,"mNowHealthyStep":0,"mTotalActiveTime":21249.970553013482,"mTimeUnit":600000,"mStepCount":13,"mRunStepCount":0,"mStartTime":0},{"mSpeed":0,"mCalorie":0,"mDistance":0,"mWalkStepCount":0,"mNowHealthyStep":0,"mTotalActiveTime":0,"mTimeUnit":600000,"mStepCount":0,"mRunStepCount":0,"mStartTime":0},{"mSpeed":2.8957955837249756,"mCalorie":0.71513399999999994,"mDistance":13.75,"mWalkStepCount":22,"mNowHealthyStep":0,"mTotalActiveTime":17093.74870287166,"mTimeUnit":600000,"mStepCount":22,"mRunStepCount":0,"mStartTime":0},{"mSpeed":2.7012770175933838,"mCalorie":1.4229310000000002,"mDistance":26.109999000000002,"mWalkStepCount":33,"mNowHealthyStep":0,"mTotalActiveTime":34796.875334286538,"mTimeUnit":600000,"mStepCount":33,"mRunStepCount":0,"mStartTime":0},{"mSpeed":0,"mCalorie":0,"mDistance":0,"mWalkStepCount":0,"mNowHealthyStep":0,"mTotalActiveTime":0,"mTimeUnit":600000,"mStepCount":0,"mRunStepCount":0,"mStartTime":0},{"mSpeed":0,"mCalorie":0,"mDistance":0,"mWalkStepCount":0,"mNowHealthyStep":0,"mTotalActiveTime":0,"mTimeUnit":600000,"mStepCount":0,"mRunStepCount":0,"mStartTime":0},{"mSpeed":0,"mCalorie":0,"mDistance":0,"mWalkStepCount":0,"mNowHealthyStep":0,"mTotalActiveTime":0,"mTimeUnit":600000,"mStepCount":0,"mRunStepCount":0,"mStartTime":0},{"mSpeed":0,"mCalorie":0,"mDistance":0,"mWalkStepCount":0,"mNowHealthyStep":0,"mTotalActiveTime":0,"mTimeUnit":600000,"mStepCount":0,"mRunStepCount":0,"mStartTime":0},{"mSpeed":4.1420440673828125,"mCalorie":5.0137149999999995,"mDistance":103.500001,"mWalkStepCount":130,"mNowHealthyStep":0,"mTotalActiveTime":89955.589358666126,"mTimeUnit":600000,"mStepCount":130,"mRunStepCount":0,"mStartTime":0},{"mSpeed":0,"mCalorie":0,"mDistance":0,"mWalkStepCount":0,"mNowHealthyStep":0,"mTotalActiveTime":0,"mTimeUnit":600000,"mStepCount":0,"mRunStepCount":0,"mStartTime":0},{"mSpeed":0,"mCalorie":0,"mDistance":0,"mWalkStepCount":0,"mNowHealthyStep":0,"mTotalActiveTime":0,"mTimeUnit":600000,"mStepCount":0,"mRunStepCount":0,"mStartTime":0},{"mSpeed":0,"mCalorie":0,"mDistance":0,"mWalkStepCount":0,"mNowHealthyStep":0,"mTotalActiveTime":0,"mTimeUnit":600000,"mStepCount":0,"mRunStepCount":0,"mStartTime":0},{"mSpeed":0,"mCalorie":0,"mDistance":0,"mWalkStepCount":0,"mNowHealthyStep":0,"mTotalActiveTime":0,"mTimeUnit":600000,"mStepCount":0,"mRunStepCount":0,"mStartTime":0},{"mSpeed":0,"mCalorie":0,"mDistance":0,"mWalkStepCount":0,"mNowHealthyStep":0,"mTotalActiveTime":0,"mTimeUnit":600000,"mStepCount":0,"mRunStepCount":0,"mStartTime":0},{"mSpeed":0,"mCalorie":0,"mDistance":0,"mWalkStepCount":0,"mNowHealthyStep":0,"mTotalActiveTime":0,"mTimeUnit":600000,"mStepCount":0,"mRunStepCount":0,"mStartTime":0},{"mSpeed":0,"mCalorie":0,"mDistance":0,"mWalkStepCount":0,"mNowHealthyStep":0,"mTotalActiveTime":0,"mTimeUnit":600000,"mStepCount":0,"mRunStepCount":0,"mStartTime":0},{"mSpeed":2.9805119037628174,"mCalorie":1.5135689999999999,"mDistance":27.799999,"mWalkStepCount":38,"mNowHealthyStep":0,"mTotalActiveTime":33578.123366543725,"mTimeUnit":600000,"mStepCount":38,"mRunStepCount":0,"mStartTime":0},{"mSpeed":0,"mCalorie":0,"mDistance":0,"mWalkStepCount":0,"mNowHealthyStep":0,"mTotalActiveTime":0,"mTimeUnit":600000,"mStepCount":0,"mRunStepCount":0,"mStartTime":0},{"mSpeed":0,"mCalorie":0,"mDistance":0,"mWalkStepCount":0,"mNowHealthyStep":0,"mTotalActiveTime":0,"mTimeUnit":600000,"mStepCount":0,"mRunStepCount":0,"mStartTime":0},{"mSpeed":0,"mCalorie":0,"mDistance":0,"mWalkStepCount":0,"mNowHealthyStep":0,"mTotalActiveTime":0,"mTimeUnit":600000,"mStepCount":0,"mRunStepCount":0,"mStartTime":0},{"mSpeed":0,"mCalorie":0,"mDistance":0,"mWalkStepCount":0,"mNowHealthyStep":0,"mTotalActiveTime":0,"mTimeUnit":600000,"mStepCount":0,"mRunStepCount":0,"mStartTime":0},{"mSpeed":0,"mCalorie":0,"mDistance":0,"mWalkStepCount":0,"mNowHealthyStep":0,"mTotalActiveTime":0,"mTimeUnit":600000,"mStepCount":0,"mRunStepCount":0,"mStartTime":0},{"mSpeed":0,"mCalorie":0,"mDistance":0,"mWalkStepCount":0,"mNowHealthyStep":0,"mTotalActiveTime":0,"mTimeUnit":600000,"mStepCount":0,"mRunStepCount":0,"mStartTime":0},{"mSpeed":0,"mCalorie":0,"mDistance":0,"mWalkStepCount":0,"mNowHealthyStep":0,"mTotalActiveTime":0,"mTimeUnit":600000,"mStepCount":0,"mRunStepCount":0,"mStartTime":0},{"mSpeed":0,"mCalorie":0,"mDistance":0,"mWalkStepCount":0,"mNowHealthyStep":0,"mTotalActiveTime":0,"mTimeUnit":600000,"mStepCount":0,"mRunStepCount":0,"mStartTime":0},{"mSpeed":0,"mCalorie":0,"mDistance":0,"mWalkStepCount":0,"mNowHealthyStep":0,"mTotalActiveTime":0,"mTimeUnit":600000,"mStepCount":0,"mRunStepCount":0,"mStartTime":0},{"mSpeed":0,"mCalorie":0,"mDistance":0,"mWalkStepCount":0,"mNowHealthyStep":0,"mTotalActiveTime":0,"mTimeUnit":600000,"mStepCount":0,"mRunStepCount":0,"mStartTime":0},{"mSpeed":0,"mCalorie":0,"mDistance":0,"mWalkStepCount":0,"mNowHealthyStep":0,"mTotalActiveTime":0,"mTimeUnit":600000,"mStepCount":0,"mRunStepCount":0,"mStartTime":0},{"mSpeed":0,"mCalorie":0,"mDistance":0,"mWalkStepCount":0,"mNowHealthyStep":0,"mTotalActiveTime":0,"mTimeUnit":600000,"mStepCount":0,"mRunStepCount":0,"mStartTime":0},{"mSpeed":0,"mCalorie":0,"mDistance":0,"mWalkStepCount":0,"mNowHealthyStep":0,"mTotalActiveTime":0,"mTimeUnit":600000,"mStepCount":0,"mRunStepCount":0,"mStartTime":0},{"mSpeed":0,"mCalorie":0,"mDistance":0,"mWalkStepCount":0,"mNowHealthyStep":0,"mTotalActiveTime":0,"mTimeUnit":600000,"mStepCount":0,"mRunStepCount":0,"mStartTime":0},{"mSpeed":1.3843835592269897,"mCalorie":0.91223100000000001,"mDistance":11.17,"mWalkStepCount":13,"mNowHealthyStep":0,"mTotalActiveTime":29046.863300264504,"mTimeUnit":600000,"mStepCount":13,"mRunStepCount":0,"mStartTime":0},{"mSpeed":2.1027631759643555,"mCalorie":1.2140499999999999,"mDistance":19.539999999999999,"mWalkStepCount":28,"mNowHealthyStep":0,"mTotalActiveTime":33453.123591201664,"mTimeUnit":600000,"mStepCount":28,"mRunStepCount":0,"mStartTime":0},{"mSpeed":0,"mCalorie":0,"mDistance":0,"mWalkStepCount":0,"mNowHealthyStep":0,"mTotalActiveTime":0,"mTimeUnit":600000,"mStepCount":0,"mRunStepCount":0,"mStartTime":0},{"mSpeed":0,"mCalorie":0,"mDistance":0,"mWalkStepCount":0,"mNowHealthyStep":0,"mTotalActiveTime":0,"mTimeUnit":600000,"mStepCount":0,"mRunStepCount":0,"mStartTime":0},{"mSpeed":0,"mCalorie":0,"mDistance":0,"mWalkStepCount":0,"mNowHealthyStep":0,"mTotalActiveTime":0,"mTimeUnit":600000,"mStepCount":0,"mRunStepCount":0,"mStartTime":0},{"mSpeed":0,"mCalorie":0,"mDistance":0,"mWalkStepCount":0,"mNowHealthyStep":0,"mTotalActiveTime":0,"mTimeUnit":600000,"mStepCount":0,"mRunStepCount":0,"mStartTime":0},{"mSpeed":0,"mCalorie":0,"mDistance":0,"mWalkStepCount":0,"mNowHealthyStep":0,"mTotalActiveTime":0,"mTimeUnit":600000,"mStepCount":0,"mRunStepCount":0,"mStartTime":0},{"mSpeed":0,"mCalorie":0,"mDistance":0,"mWalkStepCount":0,"mNowHealthyStep":0,"mTotalActiveTime":0,"mTimeUnit":600000,"mStepCount":0,"mRunStepCount":0,"mStartTime":0},{"mSpeed":0,"mCalorie":0,"mDistance":0,"mWalkStepCount":0,"mNowHealthyStep":0,"mTotalActiveTime":0,"mTimeUnit":600000,"mStepCount":0,"mRunStepCount":0,"mStartTime":0},{"mSpeed":0,"mCalorie":0,"mDistance":0,"mWalkStepCount":0,"mNowHealthyStep":0,"mTotalActiveTime":0,"mTimeUnit":600000,"mStepCount":0,"mRunStepCount":0,"mStartTime":0},{"mSpeed":0,"mCalorie":0,"mDistance":0,"mWalkStepCount":0,"mNowHealthyStep":0,"mTotalActiveTime":0,"mTimeUnit":600000,"mStepCount":0,"mRunStepCount":0,"mStartTime":0}]